lenk.py
lenk-1.1.dist-info/DESCRIPTION.rst
lenk-1.1.dist-info/METADATA
lenk-1.1.dist-info/metadata.json
lenk-1.1.dist-info/RECORD
lenk-1.1.dist-info/top_level.txt
lenk-1.1.dist-info/WHEEL
