Metadata-Version: 2.0
Name: lenk
Version: 1.1
Summary: A dictionary that always finds what it's looking for.
Home-page: https://github.com/briancurtin/lenk
Author: Brian Curtin
Author-email: brian@python.org
License: Apache Software License
Platform: UNKNOWN
Classifier: Development Status :: 5 - Production/Stable
Classifier: Intended Audience :: Developers
Classifier: License :: OSI Approved :: Apache Software License
Classifier: Programming Language :: Python
Classifier: Programming Language :: Python :: 2
Classifier: Programming Language :: Python :: 3
